MANIFEST.in
README.rst
setup.py
collective/__init__.py
collective.mediaelementjs.egg-info/PKG-INFO
collective.mediaelementjs.egg-info/SOURCES.txt
collective.mediaelementjs.egg-info/dependency_links.txt
collective.mediaelementjs.egg-info/entry_points.txt
collective.mediaelementjs.egg-info/namespace_packages.txt
collective.mediaelementjs.egg-info/not-zip-safe
collective.mediaelementjs.egg-info/requires.txt
collective.mediaelementjs.egg-info/top_level.txt
collective/mediaelementjs/README.txt
collective/mediaelementjs/__init__.py
collective/mediaelementjs/behaviors.py
collective/mediaelementjs/configure.zcml
collective/mediaelementjs/dexterity.py
collective/mediaelementjs/dexterity.zcml
collective/mediaelementjs/events.py
collective/mediaelementjs/interfaces.py
collective/mediaelementjs/media.py
collective/mediaelementjs/metadata_extraction.py
collective/mediaelementjs/metadata_extraction.txt
collective/mediaelementjs/upgrades.zcml
collective/mediaelementjs/browser/__init__.py
collective/mediaelementjs/browser/configure.zcml
collective/mediaelementjs/browser/file.pt
collective/mediaelementjs/browser/file4x.pt
collective/mediaelementjs/browser/file_view.pt
collective/mediaelementjs/browser/medialement-integration.js
collective/mediaelementjs/browser/view.py
collective/mediaelementjs/browser/mediaelementjs/background.png
collective/mediaelementjs/browser/mediaelementjs/bigplay.fw.png
collective/mediaelementjs/browser/mediaelementjs/bigplay.png
collective/mediaelementjs/browser/mediaelementjs/bigplay.svg
collective/mediaelementjs/browser/mediaelementjs/controls-ted.png
collective/mediaelementjs/browser/mediaelementjs/controls-wmp-bg.png
collective/mediaelementjs/browser/mediaelementjs/controls-wmp.png
collective/mediaelementjs/browser/mediaelementjs/controls.fw.png
collective/mediaelementjs/browser/mediaelementjs/controls.png
collective/mediaelementjs/browser/mediaelementjs/controls.svg
collective/mediaelementjs/browser/mediaelementjs/flashmediaelement-cdn.swf
collective/mediaelementjs/browser/mediaelementjs/flashmediaelement-debug.swf
collective/mediaelementjs/browser/mediaelementjs/flashmediaelement.swf
collective/mediaelementjs/browser/mediaelementjs/jquery.js
collective/mediaelementjs/browser/mediaelementjs/jumpforward.png
collective/mediaelementjs/browser/mediaelementjs/loading.gif
collective/mediaelementjs/browser/mediaelementjs/mediaelement-and-player.js
