Metadata-Version: 1.1
Name: collective.mediaelementjs
Version: 0.4.3
Summary: A simple integration of the MediaElementJS video player for Plone.
Home-page: https://github.com/collective/collective.mediaelementjs
Author: Servilio Afre Puentes
Author-email: afrepues@mcmaster.ca
License: GPL
Keywords: plone html5 audio video mp3 wma mp4 webm ogg flv wmv mpeg quicktime
Platform: UNKNOWN
Classifier: Environment :: Web Environment
Classifier: License :: OSI Approved :: GNU General Public License (GPL)
Classifier: Operating System :: OS Independent
Classifier: Framework :: Zope2
Classifier: Framework :: Plone
Classifier: Framework :: Plone :: 4.0
Classifier: Framework :: Plone :: 4.1
Classifier: Framework :: Plone :: 4.2
Classifier: Framework :: Plone :: 4.3
Classifier: Programming Language :: Python
Classifier: Programming Language :: Python :: 2.6
Classifier: Programming Language :: Python :: 2.7
Classifier: Topic :: Multimedia :: Video :: Display
Classifier: Topic :: Multimedia :: Sound/Audio :: Players
Classifier: Topic :: Multimedia :: Sound/Audio :: Players :: MP3
